dl_pipeline/__init__.py
dl_pipeline/_nbdev.py
dl_pipeline/core.py
dl_pipeline/audio/__init__.py
dl_pipeline/audio/all.py
dl_pipeline/audio/augmentations.py
dl_pipeline/audio/core.py
dl_pipeline/audio/dataset.py
dl_pipeline/audio/models.py
dl_pipeline/audio/util.py
dl_pipeline/external/__init__.py
dl_pipeline/external/xresnet_ssa.py
dl_pipeline/kaggle/__init__.py
dl_pipeline/kaggle/rfcx_species_audio_detection.py
dl_pipeline/vision/__init__.py
dl_pipeline/vision/losses.py
dl_pipeline/vision/models.py
dl_pipeline/vision/triplet.py
dl_pipeline-0.0.1.dist-info/LICENSE
dl_pipeline-0.0.1.dist-info/METADATA
dl_pipeline-0.0.1.dist-info/WHEEL
dl_pipeline-0.0.1.dist-info/entry_points.txt
dl_pipeline-0.0.1.dist-info/top_level.txt
dl_pipeline-0.0.1.dist-info/RECORD
