Metadata-Version: 2.1
Name: dl-pipeline
Version: 0.0.1
Summary: A Deep Learning Pipeline
Home-page: https://github.com/mnpinto/dl_pipeline/tree/master/
Author: Miguel Pinto
Author-email: mnpinto@fc.ul.pt
License: Apache Software License 2.0
Keywords: deep learning,kaggle
Platform: UNKNOWN
Classifier: Development Status :: 3 - Alpha
Classifier: Intended Audience :: Developers
Classifier: License :: OSI Approved :: Apache Software License
Classifier: Natural Language :: English
Classifier: Programming Language :: Python :: 3.6
Classifier: Programming Language :: Python :: 3.7
Classifier: Programming Language :: Python :: 3.8
Requires-Python: >=3.6
Requires-Dist: fastcore
Requires-Dist: fastai
Requires-Dist: nbdev
Requires-Dist: efficientnet-pytorch
Requires-Dist: timm
